ula.vhd
-- =============================================================================
--  ula.vhd  --  Unidade Lógica e Aritmética  --  RISC-V 32-bit Monociclo
-- =============================================================================
--
--  Operações (op):
--    0000 = ADD    0001 = SUB    0010 = AND    0011 = OR
--    0100 = XOR    0101 = SLL    0110 = SRL    0111 = SRA
--    1000 = SLT    1001 = SLTU
--
--  Saídas:
--    res  : resultado de 32 bits
--    zero : '1' quando res = 0  (usado por BEQ/BNE)
--
-- Funções úteis: 
--   SLL : std_logic_vector(shift_left (unsigned(i_a), shamt))
--   SRL : std_logic_vector(shift_right (unsigned(i_a), shamt))
--   SRA : std_logic_vector(shift_right (signed(i_a), shamt))
--
-- Dicas: 
-- SLT : res 1 quando a < b (com sinal)
-- SLTU : res 1 quando a < b (sem sinal)
-- =============================================================================

library ieee;
use ieee.std_logic_1164.all;
use ieee.numeric_std.all;

entity ula is
    port (
        a, b : in std_logic_vector(31 downto 0);
        op : in std_logic_vector(3 downto 0);
        res : out std_logic_vector(31 downto 0);
        zero : out std_logic
    );
end ula;

architecture arch of ula is
    signal result : std_logic_vector(31 downto 0);
begin
    process(a, b, op)
    begin
        if op = "0000" then
            result <= std_logic_vector(signed(a) + signed(b));
        elsif op = "0001" then
            result <= std_logic_vector(signed(a) - signed(b));
        elsif op = "0010" then
            result <= a and b;
        elsif op = "0011" then
            result <= a or b;
        elsif op = "0100" then
            result <= a xor b;
        elsif op = "0101" then
            result <= std_logic_vector(shift_left(unsigned(a), to_integer(unsigned(b(4 downto 0)))));
        elsif op = "0110" then  
            result <= std_logic_vector(shift_right(unsigned(a), to_integer(unsigned(b(4 downto 0)))));
        elsif op = "0111" then
            result <= std_logic_vector(shift_right(signed(a), to_integer(unsigned(b(4 downto 0)))));
        elsif op = "1000" then
            if signed(a) < signed(b) then
                result <= "00000000000000000000000000000001";
            else
                result <= (others => '0');
            end if;
        elsif op = "1001" then
            if unsigned(a) < unsigned(b) then
                result <= "00000000000000000000000000000001";
            else
                result <= (others => '0');
            end if;
        else
            result <= (others => '0');
        end if;
    end process;
    
    process(result)
    begin
        res <= result;
        if result = "00000000000000000000000000000000" then
            zero <= '1';
        else
            zero <= '0';
        end if;
    end process;
end arch;

ulaop.vhd
library ieee;
use ieee.std_logic_1164.all;

entity ulaop is
    port (
        first3bits : in  std_logic_vector(2 downto 0);
        last1bit   : in  std_logic;
        ualop_out  : out std_logic_vector(3 downto 0)
    );
end ulaop;

architecture arch of ulaop is
begin

    -- 0000 = ADD    0001 = SUB    0010 = AND    0011 = OR
    -- 0100 = XOR    0101 = SLL    0110 = SRL    0111 = SRA
    -- 1000 = SLT    1001 = SLTU

    process(first3bits, last1bit)
    begin
        case first3bits is
            when "000" =>
                if last1bit = '0' then
                    ualop_out <= "0000"; -- ADD
                else
                    ualop_out <= "0001"; -- SUB
                end if;

            when "001" =>
                ualop_out <= "0101"; -- SLL
            
            when "010" =>
                ualop_out <= "1000"; -- SLT

            when "011" =>
                ualop_out <= "1001"; -- SLTU

            when "100" =>
                ualop_out <= "0100"; -- XOR

            when "101" =>
                if last1bit = '0' then
                    ualop_out <= "0110"; -- SRL
                else
                    ualop_out <= "0111"; -- SRA
                end if;

            when "110" =>
                ualop_out <= "0011"; -- OR

            when "111" =>
                ualop_out <= "0010"; -- AND

            when others =>
                ualop_out <= (others => '0');
        end case;
    end process;

end architecture arch;

mux.vhd
library ieee;
use ieee.std_logic_1164.all;

entity mux is
    port (
        a, b : in std_logic;
        sel : in std_logic;
        o : out std_logic
    );
end mux;

architecture arch of mux is
begin
    process(a, b, sel)
    begin
        if sel = '0' then
            o <= a;
        else
            o <= b;
        end if;
    end process;
end arch;

design.vhd
library ieee;
use ieee.std_logic_1164.all;
use ieee.numeric_std.all;

entity design is
    port (
        ins : in std_logic_vector(31 downto 0); -- Instrução

        immediate : in std_logic_vector(31 downto 0);            -- Imediato
        reg_out_1, reg_out_2 : in std_logic_vector(31 downto 0); -- Saída do banco de registradores
        ctrl_ual_fonte : in std_logic;                           -- responde Imediato Ou Registrador?
        
        ual_res : out std_logic_vector(31 downto 0); -- Saída da UAL
        ual_zero : out std_logic
        );
end design;

architecture arch of design is
    signal mux_out : std_logic_vector(31 downto 0);
    signal ualop_out : std_logic_vector(3 downto 0);
    signal ins_signal : std_logic_vector(31 downto 0);
begin
    ins_signal <= ins;
    MUX: entity work.mux
        port map (
            a => reg_out_2,
            b => immediate,
            sel => ctrl_ual_fonte,
            o => mux_out
        );
    ULAOP: entity work.ulaop
        port map (
            first3bits => ins_signal(14 downto 12),
            last1bit => ins(30),
            ualop_out => ualop_out
        );
    ULA: entity work.ula
        port map (
            a => reg_out_1,
            b => mux_out,
            op => ualop_out,
            res => ual_res,
            zero => ual_zero
        );
end arch;

testbench.vhd
library ieee;
use ieee.std_logic_1164.all;

entity testbench is
end testbench;

architecture arch of testbench is
    signal immediate, reg_out_1, reg_out_2, ins : std_logic_vector(31 downto 0);
    signal ctrl_ual_fonte : std_logic;
    signal ual_res : std_logic_vector(31 downto 0);
    signal ual_zero : std_logic;
begin
    DUT: entity work.design
        port map (
            ins => ins,
            
            immediate => immediate,
            reg_out_1 => reg_out_1,
            reg_out_2 => reg_out_2,
            ctrl_ual_fonte => ctrl_ual_fonte,

            ual_res => ual_res,
            ual_zero => ual_zero
        );
    process
    begin
        ins <= (others => '0');
        immediate <= (others => '0');
        reg_out_1 <= (others => '0'); reg_out_2 <= (others => '0');
        ctrl_ual_fonte <= '0';
        wait for 10 ns;
        ----- Teste a seguir: testar mux do immediate e do reg_out_2
        reg_out_1 <= "00000000000000000000000000000111"; -- 7
        reg_out_2 <= "00000000000000000000000000000101"; -- 5 
        immediate <= "00000000000000000000000000001001"; -- 9
        wait for 10 ns;
        ctrl_ual_fonte <= '1';
        ----- TESTE ACIMA FUNCIONOU
        -- Teste a seguir: testar saída do controle "ualop"
        --
        -- resultados:
        -- 0000 = ADD    0001 = SUB    0010 = AND    0011 = OR
        -- 0100 = XOR    0101 = SLL    0110 = SRL    0111 = SRA
        -- 1000 = SLT    1001 = SLTU
        --
        wait for 10 ns;
        ins <= "0000000" & "00000" & "00000" & "000" & "00000" & "0110011"; -- 0000 = ADD
        wait for 10 ns;
        ins <= "0100000" & "00000" & "00000" & "000" & "00000" & "0110011"; -- 0001 = SUB
        wait for 10 ns;
        ins <= "0000000" & "00000" & "00000" & "111" & "00000" & "0110011"; -- 0010 = AND
        wait for 10 ns;
        ins <= "0000000" & "00000" & "00000" & "110" & "00000" & "0110011"; -- 0011 = OR
        
        wait for 10 ns;
        ins <= "0000000" & "00000" & "00000" & "100" & "00000" & "0110011"; -- 0100 = XOR
        wait for 10 ns;
        ins <= "0000000" & "00000" & "00000" & "001" & "00000" & "0110011"; -- 0101 = SLL
        wait for 10 ns;
        ins <= "0000000" & "00000" & "00000" & "101" & "00000" & "0110011"; -- 0110 = SRL
        wait for 10 ns;
        ins <= "0100000" & "00000" & "00000" & "101" & "00000" & "0110011"; -- 0111 = SRA

        wait for 10 ns;
        ins <= "0000000" & "00000" & "00000" & "010" & "00000" & "0110011"; -- 1000 = SLT
        wait for 10 ns;
        ins <= "0000000" & "00000" & "00000" & "011" & "00000" & "0110011"; -- 1001 = SLTU
        
        wait for 10 ns;
        wait;
    end process;
end;

wave.vcd
$date
  Tue Jun 30 09:44:19 2026
$end
$version
  GHDL v0
$end
$timescale
  1 fs
$end
$scope module standard $end
$upscope $end
$scope module std_logic_1164 $end
$upscope $end
$scope module numeric_std $end
$upscope $end
$scope module testbench $end
$var reg 32 ! immediate[31:0] $end
$var reg 32 " reg_out_1[31:0] $end
$var reg 32 # reg_out_2[31:0] $end
$var reg 32 $ ins[31:0] $end
$var reg 1 % ctrl_ual_fonte $end
$var reg 32 & ual_res[31:0] $end
$var reg 1 ' ual_zero $end
$scope module dut $end
$var reg 32 ( ins[31:0] $end
$var reg 32 ) immediate[31:0] $end
$var reg 32 * reg_out_1[31:0] $end
$var reg 32 + reg_out_2[31:0] $end
$var reg 1 , ctrl_ual_fonte $end
$var reg 32 - ual_res[31:0] $end
$var reg 1 . ual_zero $end
$var reg 32 / mux_out[31:0] $end
$var reg 4 0 ualop_out[3:0] $end
$var reg 32 1 ins_signal[31:0] $end
$scope module mux $end
$var reg 32 2 a[31:0] $end
$var reg 32 3 b[31:0] $end
$var reg 1 4 sel $end
$var reg 32 5 o[31:0] $end
$upscope $end
$scope module ulaop $end
$var reg 3 6 first3bits[2:0] $end
$var reg 1 7 last1bit $end
$var reg 4 8 ualop_out[3:0] $end
$upscope $end
$scope module ula $end
$var reg 32 9 a[31:0] $end
$var reg 32 : b[31:0] $end
$var reg 4 ; op[3:0] $end
$var reg 32 < res[31:0] $end
$var reg 1 = zero $end
$var reg 32 > result[31:0] $end
$upscope $end
$upscope $end
$upscope $end
$enddefinitions $end
#0
b00000000000000000000000000000000 !
b00000000000000000000000000000000 "
b00000000000000000000000000000000 #
b00000000000000000000000000000000 $
0%
b00000000000000000000000000000000 &
1'
b00000000000000000000000000000000 (
b00000000000000000000000000000000 )
b00000000000000000000000000000000 *
b00000000000000000000000000000000 +
0,
b00000000000000000000000000000000 -
1.
b00000000000000000000000000000000 /
b0000 0
b00000000000000000000000000000000 1
b00000000000000000000000000000000 2
b00000000000000000000000000000000 3
04
b00000000000000000000000000000000 5
b000 6
07
b0000 8
b00000000000000000000000000000000 9
b00000000000000000000000000000000 :
b0000 ;
b00000000000000000000000000000000 <
1=
b00000000000000000000000000000000 >
#10000000
b00000000000000000000000000001001 !
b00000000000000000000000000000111 "
b00000000000000000000000000000101 #
b00000000000000000000000000001100 &
0'
b00000000000000000000000000001001 )
b00000000000000000000000000000111 *
b00000000000000000000000000000101 +
b00000000000000000000000000001100 -
0.
b00000000000000000000000000000101 /
b00000000000000000000000000000101 2
b00000000000000000000000000001001 3
b00000000000000000000000000000101 5
b00000000000000000000000000000111 9
b00000000000000000000000000000101 :
b00000000000000000000000000001100 <
0=
b00000000000000000000000000001100 >
#20000000
1%
b00000000000000000000000000010000 &
1,
b00000000000000000000000000010000 -
b00000000000000000000000000001001 /
14
b00000000000000000000000000001001 5
b00000000000000000000000000001001 :
b00000000000000000000000000010000 <
b00000000000000000000000000010000 >
#30000000
b00000000000000000000000000110011 $
b00000000000000000000000000110011 (
b00000000000000000000000000110011 1
#40000000
b01000000000000000000000000110011 $
b11111111111111111111111111111110 &
b01000000000000000000000000110011 (
b11111111111111111111111111111110 -
b0001 0
b01000000000000000000000000110011 1
17
b0001 8
b0001 ;
b11111111111111111111111111111110 <
b11111111111111111111111111111110 >
#50000000
b00000000000000000111000000110011 $
b00000000000000000000000000000001 &
b00000000000000000111000000110011 (
b00000000000000000000000000000001 -
b0010 0
b00000000000000000111000000110011 1
b111 6
07
b0010 8
b0010 ;
b00000000000000000000000000000001 <
b00000000000000000000000000000001 >
#60000000
b00000000000000000110000000110011 $
b00000000000000000000000000001111 &
b00000000000000000110000000110011 (
b00000000000000000000000000001111 -
b0011 0
b00000000000000000110000000110011 1
b110 6
b0011 8
b0011 ;
b00000000000000000000000000001111 <
b00000000000000000000000000001111 >
#70000000
b00000000000000000100000000110011 $
b00000000000000000000000000001110 &
b00000000000000000100000000110011 (
b00000000000000000000000000001110 -
b0100 0
b00000000000000000100000000110011 1
b100 6
b0100 8
b0100 ;
b00000000000000000000000000001110 <
b00000000000000000000000000001110 >
#80000000
b00000000000000000001000000110011 $
b00000000000000000000111000000000 &
b00000000000000000001000000110011 (
b00000000000000000000111000000000 -
b0101 0
b00000000000000000001000000110011 1
b001 6
b0101 8
b0101 ;
b00000000000000000000111000000000 <
b00000000000000000000111000000000 >
#90000000
b00000000000000000101000000110011 $
b00000000000000000000000000000000 &
1'
b00000000000000000101000000110011 (
b00000000000000000000000000000000 -
1.
b0110 0
b00000000000000000101000000110011 1
b101 6
b0110 8
b0110 ;
b00000000000000000000000000000000 <
1=
b00000000000000000000000000000000 >
#100000000
b01000000000000000101000000110011 $
b01000000000000000101000000110011 (
b0111 0
b01000000000000000101000000110011 1
17
b0111 8
b0111 ;
#110000000
b00000000000000000010000000110011 $
b00000000000000000000000000000001 &
0'
b00000000000000000010000000110011 (
b00000000000000000000000000000001 -
0.
b1000 0
b00000000000000000010000000110011 1
b010 6
07
b1000 8
b1000 ;
b00000000000000000000000000000001 <
0=
b00000000000000000000000000000001 >
#120000000
b00000000000000000011000000110011 $
b00000000000000000011000000110011 (
b1001 0
b00000000000000000011000000110011 1
b011 6
b1001 8
b1001 ;
