ula.vhd
-- =============================================================================
--  ula.vhd  --  Unidade Lógica e Aritmética  --  RISC-V 32-bit Monociclo
-- =============================================================================
--
--  Operações (op):
--    0000 = ADD    0001 = SUB    0010 = AND    0011 = OR
--    0100 = XOR    0101 = SLL    0110 = SRL    0111 = SRA
--    1000 = SLT    1001 = SLTU
--
--  Saídas:
--    res  : resultado de 32 bits
--    zero : '1' quando res = 0  (usado por BEQ/BNE)
--
-- Funções úteis: 
--   SLL : std_logic_vector(shift_left (unsigned(i_a), shamt))
--   SRL : std_logic_vector(shift_right (unsigned(i_a), shamt))
--   SRA : std_logic_vector(shift_right (signed(i_a), shamt))
--
-- Dicas: 
-- SLT : res 1 quando a < b (com sinal)
-- SLTU : res 1 quando a < b (sem sinal)
-- =============================================================================

library ieee;
use ieee.std_logic_1164.all;
use ieee.numeric_std.all;

entity ula is
    port (
        a, b : in std_logic_vector(31 downto 0);
        op : in std_logic_vector(3 downto 0);
        res : out std_logic_vector(31 downto 0);
        zero : out std_logic
    );
end ula;

architecture arch of ula is
    signal result : std_logic_vector(31 downto 0);
begin
    process(a, b, op)
    begin
        if op = "0000" then
            result <= std_logic_vector(signed(a) + signed(b));
        elsif op = "0001" then
            result <= std_logic_vector(signed(a) - signed(b));
        elsif op = "0010" then
            result <= a and b;
        elsif op = "0011" then
            result <= a or b;
        elsif op = "0100" then
            result <= a xor b;
        elsif op = "0101" then
            result <= std_logic_vector(shift_left(unsigned(a), to_integer(unsigned(b(4 downto 0)))));
        elsif op = "0110" then  
            result <= std_logic_vector(shift_right(unsigned(a), to_integer(unsigned(b(4 downto 0)))));
        elsif op = "0111" then
            result <= std_logic_vector(shift_right(signed(a), to_integer(unsigned(b(4 downto 0)))));
        elsif op = "1000" then
            if signed(a) < signed(b) then
                result <= "00000000000000000000000000000001";
            else
                result <= (others => '0');
            end if;
        elsif op = "1001" then
            if unsigned(a) < unsigned(b) then
                result <= "00000000000000000000000000000001";
            else
                result <= (others => '0');
            end if;
        else
            result <= (others => '0');
        end if;
    end process;
    
    process(result)
    begin
        res <= result;
        if result = "00000000000000000000000000000000" then
            zero <= '1';
        else
            zero <= '0';
        end if;
    end process;
end arch;

testbench.vhd
library ieee;
use ieee.std_logic_1164.all;

entity testbench is
end testbench;

architecture arch of testbench is
    signal a, b, res : std_logic_vector(31 downto 0);
    signal op : std_logic_vector(3 downto 0);
    signal zero : std_logic;
begin
    DUT: entity work.Ula
        port map (
            a => a,
            b => b,
            op => op,
            res => res,
            zero => zero
        );
    process
    begin
        a <= "00000000000000000000000000001001"; -- 9
        b <= "00000000000000000000000000000111"; -- 7
        op <= "0000"; -- ADD
        wait for 10 ns;
        op <= "0001"; -- SUB
        wait for 10 ns;
        op <= "0010"; -- AND
        wait for 10 ns;
        op <= "0011"; -- OR
        wait for 10 ns;
        op <= "0100"; -- XOR
        wait for 10 ns;
        op <= "0101"; -- SLL
        wait for 10 ns;
        a <= "00000000000000000000111100000000";
        b <= "00000000000000000000000000001000";
        op <= "0110"; -- SRL
        wait for 10 ns;
        op <= "0111"; -- SRA
        wait for 10 ns;
        op <= "1000"; -- SLT
        wait for 10 ns;
        op <= "1001"; -- SLTU
        wait for 10 ns;
        wait;
    end process;
end;

wave.vcd
$date
  Sun Jun 21 20:45:41 2026
$end
$version
  GHDL v0
$end
$timescale
  1 fs
$end
$scope module standard $end
$upscope $end
$scope module std_logic_1164 $end
$upscope $end
$scope module numeric_std $end
$upscope $end
$scope module testbench $end
$var reg 32 ! a[31:0] $end
$var reg 32 " b[31:0] $end
$var reg 32 # res[31:0] $end
$var reg 4 $ op[3:0] $end
$var reg 1 % zero $end
$scope module dut $end
$var reg 32 & a[31:0] $end
$var reg 32 ' b[31:0] $end
$var reg 4 ( op[3:0] $end
$var reg 32 ) res[31:0] $end
$var reg 1 * zero $end
$var reg 32 + result[31:0] $end
$upscope $end
$upscope $end
$enddefinitions $end
#0
b00000000000000000000000000001001 !
b00000000000000000000000000000111 "
b00000000000000000000000000010000 #
b0000 $
0%
b00000000000000000000000000001001 &
b00000000000000000000000000000111 '
b0000 (
b00000000000000000000000000010000 )
0*
b00000000000000000000000000010000 +
#10000000
b00000000000000000000000000000010 #
b0001 $
b0001 (
b00000000000000000000000000000010 )
b00000000000000000000000000000010 +
#20000000
b00000000000000000000000000000001 #
b0010 $
b0010 (
b00000000000000000000000000000001 )
b00000000000000000000000000000001 +
#30000000
b00000000000000000000000000001111 #
b0011 $
b0011 (
b00000000000000000000000000001111 )
b00000000000000000000000000001111 +
#40000000
b00000000000000000000000000001110 #
b0100 $
b0100 (
b00000000000000000000000000001110 )
b00000000000000000000000000001110 +
#50000000
b00000000000000000000010010000000 #
b0101 $
b0101 (
b00000000000000000000010010000000 )
b00000000000000000000010010000000 +
#60000000
b00000000000000000000111100000000 !
b00000000000000000000000000001000 "
b00000000000000000000000000001111 #
b0110 $
b00000000000000000000111100000000 &
b00000000000000000000000000001000 '
b0110 (
b00000000000000000000000000001111 )
b00000000000000000000000000001111 +
#70000000
b0111 $
b0111 (
#80000000
b00000000000000000000000000000000 #
b1000 $
1%
b1000 (
b00000000000000000000000000000000 )
1*
b00000000000000000000000000000000 +
#90000000
b1001 $
b1001 (
